high_order_layers_torch/Basis.py
high_order_layers_torch/FunctionalConvolution.py
high_order_layers_torch/FunctionalConvolutionTranspose.py
high_order_layers_torch/LagrangePolynomial.py
high_order_layers_torch/PolynomialLayers.py
high_order_layers_torch/ProductLayer.py
high_order_layers_torch/__init__.py
high_order_layers_torch/attentions.py
high_order_layers_torch/layers.py
high_order_layers_torch/modules.py
high_order_layers_torch/networks.py
high_order_layers_torch/positional_embeddings.py
high_order_layers_torch/sparse_optimizers/__init__.py
high_order_layers_torch/sparse_optimizers/sparse_lion.py
high_order_layers_torch/utils.py
high_order_layers_torch-2.6.0.dist-info/AUTHORS
high_order_layers_torch-2.6.0.dist-info/LICENSE
high_order_layers_torch-2.6.0.dist-info/METADATA
high_order_layers_torch-2.6.0.dist-info/WHEEL
high_order_layers_torch-2.6.0.dist-info/RECORD
