Metadata-Version: 2.1
Name: high-order-layers-torch
Version: 2.6.0
Summary: High order layers in pytorch
License: MIT
Author: jloverich
Author-email: john.loverich@gmail.com
Requires-Python: >=3.9,<4
Classifier: License :: OSI Approved :: MIT License
Classifier: Programming Language :: Python :: 3
Classifier: Programming Language :: Python :: 3.9
Classifier: Programming Language :: Python :: 3.10
Classifier: Programming Language :: Python :: 3.11
Classifier: Programming Language :: Python :: 3.12
Requires-Dist: hydra-core (>=1.2.0,<2.0.0)
Requires-Dist: lightning (>=2.2.5,<3.0.0)
Requires-Dist: lion-pytorch (>=0.2.2,<0.3.0)
Requires-Dist: torch (>=2.1.1)
Requires-Dist: torchmetrics (>=1.2.1,<2.0.0)
Requires-Dist: torchvision (>=0.18.0)
